parsing_project/__init__.py
parsing_project/config.py
parsing_project/file_ops.py
parsing_project/main.py
parsing_project/parser.py
parsing_project/utils.py
parsing_project-0.1.1.dist-info/licenses/LICENSE
parsing_project-0.1.1.dist-info/METADATA
parsing_project-0.1.1.dist-info/WHEEL
parsing_project-0.1.1.dist-info/entry_points.txt
parsing_project-0.1.1.dist-info/top_level.txt
parsing_project-0.1.1.dist-info/RECORD
