Metadata-Version: 2.4
Name: parsing_project
Version: 0.1.1
Summary: Invoice parsing tool for daily sales register exports
Author: Kyle Allen Levocraft
Author-email: Kyle Allen <kyle@levocraft.com>
Requires-Python: >=3.7
License-File: LICENSE
Requires-Dist: pdfplumber
Requires-Dist: regex
Dynamic: author
Dynamic: license-file
Dynamic: requires-python
